{
  "지역": "서울 성동구",
  "폐식용유": {
    "배출방법": "이물질이 섞이지 않게 모아 가까운 곳에 설치된 폐유 수거함(동 주민센터, 일부 아파트 등)에 배출해 주세요."
  },
  "폐형광등": {
    "배출방법": "깨지지 않도록 주의하여 주요거점(동 주민센터, 아파트, 주택가 골목 등)에 설치된 폐형광등 전용수거함에 배출해 주세요.",
    "주의사항": "깨진 형광등은 신문지 등으로 싸서 일반 종량제봉투로 배출해 주세요."
  },
  "의류 및 원단류": {
    "배출방법": "지역 내 설치된 의류 수거함에 배출해 주세요.",
    "주의사항": "재사용이 불가능한 의류는 특수규격마대에 담아 배출해 주세요."
  },
  "폐건전지": {
    "배출방법": "전지를 제품에서 분리하여 주요거점(동 주민센터, 아파트의 폐형광등, 폐건지 일체함 또는 편의점, 아파트 동별 우편함 등)의 전용수거함에 배출해 주세요.",
    "주의사항": "휴대폰 배터리는 휴대폰과 함께 배출해 주세요."
  },
  "백열전구, LED전구": {
    "배출방법": "신문지 등으로 싸서 일반 종량제봉투로 배출해 주세요."
  },
  "아이스팩": {
    "배출방법": "젤 아이스팩은 미개봉상태로 종량제봉투 및 특수규격마대로 배출해 주세요.",
    "주의사항": "물·전분 충전제 아이스팩은 내용물을 비우고 물로 헹궈 이물질을 제거한 후 재질별(종이류, 비닐류) 분리배출해 주세요. 대량 배출 시 특수마대로 배출해 주세요."
  }
}